transformer_discord_notifier/__init__.py
transformer_discord_notifier/discord.py
transformer_discord_notifier/transformers.py
transformer_discord_notifier-0.5.1.dist-info/AUTHORS.rst
transformer_discord_notifier-0.5.1.dist-info/LICENSE
transformer_discord_notifier-0.5.1.dist-info/METADATA
transformer_discord_notifier-0.5.1.dist-info/WHEEL
transformer_discord_notifier-0.5.1.dist-info/top_level.txt
transformer_discord_notifier-0.5.1.dist-info/RECORD
