Metadata-Version: 2.1
Name: transformer-discord-notifier
Version: 0.5.1
Summary: A Discord Notifier to send progress updates, params and results to a Discord channel.
Home-page: https://github.com/Querela/python-transformer-discord-notifier
Author: Erik Körner
Author-email: koerner@informatik.uni-leipzig.de
License: MIT
Project-URL: Documentation, https://python-transformer-discord-notifier.readthedocs.io/
Project-URL: Changelog, https://python-transformer-discord-notifier.readthedocs.io/en/latest/changelog.html
Project-URL: Issue Tracker, https://github.com/Querela/python-transformer-discord-notifier/issues
Keywords: transformers,discord.py
Platform: UNKNOWN
Classifier: Development Status :: 5 - Production/Stable
Classifier: Intended Audience :: Developers
Classifier: License :: OSI Approved :: MIT License
Classifier: Operating System :: Unix
Classifier: Operating System :: POSIX
Classifier: Operating System :: Microsoft :: Windows
Classifier: Programming Language :: Python
Classifier: Programming Language :: Python :: 3
Classifier: Programming Language :: Python :: 3.6
Classifier: Programming Language :: Python :: 3.7
Classifier: Programming Language :: Python :: 3.8
Classifier: Programming Language :: Python :: 3.9
Classifier: Programming Language :: Python :: 3.10
Classifier: Programming Language :: Python :: Implementation :: CPython
Classifier: Programming Language :: Python :: Implementation :: PyPy
Classifier: Topic :: Utilities
Requires-Python: >=3.6
Requires-Dist: transformers (<5,>=4.0.0)
Requires-Dist: discord.py
Provides-Extra: dev
Requires-Dist: docutils ; extra == 'dev'
Requires-Dist: check-manifest ; extra == 'dev'
Requires-Dist: flake8 ; extra == 'dev'
Requires-Dist: readme-renderer ; extra == 'dev'
Requires-Dist: pygments ; extra == 'dev'
Requires-Dist: isort ; extra == 'dev'
